{
	"contracts": {
		"FungibleToken": {
			"source": "",
			"aliases": {
				"testnet": "9a0766d93b6608b7"
			}
		},
		"LeagueFactory": "contracts/LeagueFactory.cdc",
		"NonFungibleToken": {
			"source": "",
			"aliases": {
				"testnet": "631e88ae7f1d7c20"
			}
		},
		"Settlement": "contracts/Settlement.cdc",
		"StakingManager": "contracts/StakingManager.cdc"
	},
	"networks": {
		"emulator": "127.0.0.1:3569",
		"mainnet": "access.mainnet.nodes.onflow.org:9000",
		"testnet": "access.devnet.nodes.onflow.org:9000"
	},
	"accounts": {
		"emulator-account": {
			"address": "f8d6e0586b0a20c7",
			"key": {
				"type": "file",
				"location": "emulator-account.pkey"
			}
		},
		"testnet-account": {
			"address": "f474649aaa285cf5",
			"key": {
				"type": "hex",
				"signatureAlgorithm": "ECDSA_secp256k1",
				"hashAlgorithm": "SHA2_256",
				"privateKey": "$TESTNET_PRIVATE_KEY"
			}
		}
	},
	"deployments": {
		"testnet": {
			"testnet-account": [
				"LeagueFactory",
				"StakingManager",
				"Settlement"
			]
		}
	}
}